[
	{
		"key": 1,
		"course": "Development",
		"first_name": "Jhankar",
		"last_name": "Mahbub",
		"image": "https://yt3.ggpht.com/ytc/AKedOLTBLMf4tq8iRjYjbmOPzLlQbD31_D2E4AOSmFPGzw=s900-c-k-c0x00ffffff-no-rj",
		"bg": "https://themezhub.net/skillup-demo/assets/img/cr-3.jpg",
		"courseName": "Advance PHP Knowledge With Laravel To Make Smart Web",
		"time": "07 hr 05 min",
		"level": "Beginer",
		"lectures": 42,
		"enrolled": "1,250",
		"star": 3,
		"cost": 129,
		"color": "#ffeaa7"
	},
	{
		"key": 2,
		"course": "Design",
		"first_name": "Karina",
		"last_name": "Islam",
		"image": "https://cdn.slidesharecdn.com/profile-photo-karinaislam35-96x96.jpg?cb=1523385294",
		"bg": "https://themezhub.net/skillup-demo/assets/img/cr-1.jpg",
		"courseName": "UI/UX Design Pattern For Succesfull Software Applications",
		"time": "10 hr 07 min",
		"level": "Beginer",
		"lectures": 67,
		"enrolled": "8,350",
		"star": 3,
		"cost": 149,
		"color": "#81ecec"
	},
	{
		"key": 3,
		"course": "Banking",
		"first_name": "Robert",
		"last_name": "Fox",
		"image": "https://randomuser.me/api/portraits/women/67.jpg",
		"bg": "https://themezhub.net/skillup-demo/assets/img/cr-2.jpg",
		"courseName": "UI/UX Design Pattern For Succesfull Software Applications",
		"time": "9 hr 17 min",
		"level": "Easy",
		"lectures": 67,
		"enrolled": "8,350",
		"star": 3,
		"cost": 137,
		"color": "#74b9ff"
	},
	{
		"key": 4,
		"course": "Accounting",
		"first_name": "Raks",
		"last_name": "Johns",
		"image": "https://randomuser.me/api/portraits/men/75.jpg",
		"bg": "https://themezhub.net/skillup-demo/assets/img/cr-4.jpg",
		"courseName": "The Complete Accounting & Bank Financial Course 2021-2022",
		"time": "11 hr 09 min",
		"level": "Beginer",
		"lectures": 58,
		"enrolled": "7,450",
		"star": 4,
		"cost": 169,
		"color": "#dfe6e9"
	},
	{
		"key": 5,
		"course": "Business Startegy",
		"first_name": "Rotina",
		"last_name": "Fox",
		"image": "https://randomuser.me/api/portraits/women/63.jpg",
		"bg": "https://themezhub.net/skillup-demo/assets/img/cr-5.jpg",
		"courseName": "The Complete Business Plan Course Includes 50 Templates of Business",
		"time": "12 hr 37 min",
		"level": "Beginer",
		"lectures": 43,
		"enrolled": "3310",
		"star": 3,
		"cost": 119,
		"color": "#00cec9"
	},
	{
		"key": 6,
		"course": "Python",
		"first_name": "Rajib",
		"last_name": "Hasan",
		"image": "https://randomuser.me/api/portraits/men/88.jpg",
		"bg": "https://themezhub.net/skillup-demo/assets/img/cr-6.jpg",
		"courseName": "Full Web Designing Course With 20 Web Template Designing",
		"time": "12 hr 04 min",
		"level": "Beginer",
		"lectures": 57,
		"enrolled": "5460",
		"star": 3,
		"cost": 199,
		"color": "#fd79a8"
	},
	{
		"key": 7,
		"course": "React",
		"first_name": "Rahman",
		"last_name": "Mia",
		"image": "https://randomuser.me/api/portraits/men/33.jpg",
		"bg": "https://themezhub.net/skillup-demo/assets/img/cr-7.jpg",
		"courseName": "Advance React Js Knowledge With Bootstrap To Make Smart Web",
		"time": "11 hr 07 min",
		"level": "Beginer",
		"lectures": 77,
		"enrolled": "9,370",
		"star": 4,
		"cost": 175,
		"color": "#ffeaa7"
	},
	{
		"key": 8,
		"course": "JavaScript",
		"first_name": "Ashtha",
		"last_name": "Fox",
		"image": "https://randomuser.me/api/portraits/women/51.jpg",
		"bg": "https://themezhub.net/skillup-demo/assets/img/cr-8.jpg",
		"courseName": "Design Pattern For Succesfull Software Applications and Maintanance",
		"time": "10 hr 07 min",
		"level": "Beginer",
		"lectures": 67,
		"enrolled": "8,350",
		"star": 3,
		"cost": 149,
		"color": "#81ecec"
	},
	{
		"key": 9,
		"course": "Android",
		"first_name": "Jona",
		"last_name": "Carlus",
		"image": "https://randomuser.me/api/portraits/women/15.jpg",
		"bg": "https://themezhub.net/skillup-demo/assets/img/cr-9.jpg",
		"courseName": "UI/UX Design Pattern For Succesfull Software Applications",
		"time": "08 hr 07 min",
		"level": "Easy",
		"lectures": 69,
		"enrolled": "5350",
		"star": 3,
		"cost": 129,
		"color": "#74b9ff"
	}
]